seeborn/__init__.py
seeborn/built_in_examples.py
seeborn/code_manager.py
seeborn/examples_viewer.py
seeborn-0.4.3.dist-info/licenses/LICENSE
seeborn-0.4.3.dist-info/METADATA
seeborn-0.4.3.dist-info/WHEEL
seeborn-0.4.3.dist-info/top_level.txt
seeborn-0.4.3.dist-info/RECORD
